polars_expr_transformer/__init__.py
polars_expr_transformer/configs/__init__.py
polars_expr_transformer/configs/settings.py
polars_expr_transformer/funcs/__init__.py
polars_expr_transformer/funcs/date_functions.py
polars_expr_transformer/funcs/logic_functions.py
polars_expr_transformer/funcs/math_functions.py
polars_expr_transformer/funcs/special_funcs.py
polars_expr_transformer/funcs/string_functions.py
polars_expr_transformer/funcs/type_conversions.py
polars_expr_transformer/funcs/utils.py
polars_expr_transformer/function_overview.py
polars_expr_transformer/main_module.py
polars_expr_transformer/process/__init__.py
polars_expr_transformer/process/hierarchy_builder.py
polars_expr_transformer/process/models.py
polars_expr_transformer/process/polars_expr_transformer.py
polars_expr_transformer/process/post_process.py
polars_expr_transformer/process/preprocess.py
polars_expr_transformer/process/process_inline.py
polars_expr_transformer/process/token_classifier.py
polars_expr_transformer/process/tokenize.py
polars_expr_transformer/schemas.py
polars_expr_transformer/visualize.py
polars_expr_transformer-0.5.0.dist-info/METADATA
polars_expr_transformer-0.5.0.dist-info/WHEEL
polars_expr_transformer-0.5.0.dist-info/licenses/LICENSE
polars_expr_transformer-0.5.0.dist-info/RECORD
