Metadata-Version: 2.4
Name: polars_expr_transformer
Version: 0.5.0
Summary: Transform string-based expressions into Polars DataFrame operations
License-File: LICENSE
Author: Edward van Eehoud
Author-email: evaneechoudl@gmail.com
Requires-Python: >=3.10
Classifier: Programming Language :: Python :: 3
Classifier: Programming Language :: Python :: 3.10
Classifier: Programming Language :: Python :: 3.11
Classifier: Programming Language :: Python :: 3.12
Classifier: Programming Language :: Python :: 3.13
Classifier: Programming Language :: Python :: 3.14
Requires-Dist: polars (>1.8.2,<2.0.0)
Requires-Dist: polars-ds (>=0.6.0)
Requires-Dist: pydantic (>=2.9.2)
Project-URL: Repository, https://github.com/edwardvaneechoud/polars_expr_transformer
